voltotg/__init__.py
voltOTG-1.0.dist-info/LICENSE
voltOTG-1.0.dist-info/METADATA
voltOTG-1.0.dist-info/WHEEL
voltOTG-1.0.dist-info/top_level.txt
voltOTG-1.0.dist-info/RECORD
