Metadata-Version: 2.1
Name: voltOTG
Version: 1.0
Summary: A package to communicate with the voltOTG usb volt-meter 
Home-page: https://github.com/gbit-is/voltOTG
Author: Gbitur
Author-email: theemosunrise@gmail.com
License: UNKNOWN
Platform: UNKNOWN
Classifier: Programming Language :: Python :: 3
Classifier: License :: OSI Approved :: MIT License
Classifier: Operating System :: POSIX :: Linux
Requires-Python: >=3.6
